releasy/__init__.py
releasy/__main__.py
releasy/constants.py
releasy/download.py
releasy/entity.py
releasy/gitparser.py
releasy/releasy.py
releasy/cli/__init__.py
releasy/cli/cli.py
releasy/cli/download.py
releasy/cli/ls.py
releasy/cli/overview.py
releasy/cli/prov.py
releasy/cli/show.py
releasy_uff-1.0.3.dist-info/METADATA
releasy_uff-1.0.3.dist-info/RECORD
releasy_uff-1.0.3.dist-info/WHEEL
releasy_uff-1.0.3.dist-info/top_level.txt
