Metadata-Version: 2.1
Name: releasy-uff
Version: 1.0.3
Summary: Releasy is a tool that collects provenance data from releases by parsing the software version control and issue tracking systems.
Home-page: https://github.com/gems-uff/releasy
Author: Felipe Curty
Author-email: felipecrp@gmail.com
License: UNKNOWN
Platform: UNKNOWN
Requires-Dist: python-dateutil
Requires-Dist: requests
